[
    {
        "name": "Repliche aggiornate ogni fine mese",
        "urlList": "https://pastebin.com/raw/ZyhME6iy",
        "imageUrl": "https://i.imgur.com/fc6Hsngm.jpg"
    },
    {
        "name": "Radio varie provvisorio",
        "urlList": "https://pastebin.com/raw/9p5paGMy",
        "imageUrl": "https://i.imgur.com/SqW4o9Rm.png",
        "onlyOneElement": true
    },
    {
        "name": "Zoo live & replica serale",
        "urlList": "https://pastebin.com/raw/Qdxk1Hzr",
        "imageUrl": "https://i.imgur.com/EkF7e82.jpg"
    },
    {
        "name": "Fight Back Mazzoliverso",
        "urlList": "https://pastebin.com/raw/FXfbZHjV",
        "imageUrl": "https://i.imgur.com/Q0EqGxnm.jpg"
    },
    {
        "name": "Video",
        "urlList": "https://pastebin.com/raw/sUcQid3M",
        "imageUrl": "https://i.imgur.com/APAQ1lb.jpg"
    },
    {
        "name": "Zoo#20",
        "urlList": "https://bit.ly/3F1d3J7",
        "imageUrl": "https://i.imgur.com/6R3MI8Rm.jpg"
    },
    {
        "name": "Zoo Music & San Jimmy",
        "urlList": "https://pastebin.com/raw/xhde73Pb",
        "imageUrl": "https://i.imgur.com/p6sZaNv.jpg"
    },
    {
        "name": "Polaroyd",
        "urlList": "https://pastebin.com/raw/JBTB511z",
        "imageUrl": "https://i.imgur.com/IYWcHGe.jpg"
    },
    {
        "name": "105 Detox",
        "urlList": "https://pastebin.com/raw/An74nyRS",
        "imageUrl": "https://i.imgur.com/LoCh3kp.jpg"
    },
    {
        "name": "Marco' s Upfront",
        "urlList": "https://pastebin.com/raw/b7Hwzge1",
        "imageUrl": "https://i.imgur.com/jKNB0lt.jpg"
    },
    {
        "name": "Sabato Sega: Mazzoli ospite su Radio Deejay (Tnx Giauz)",
        "urlList": "https://pastebin.com/raw/5feQL6nT",
        "imageUrl": "https://i.imgur.com/9qipbHem.png"
    },
    {
        "name": "Criminal Zoo",
        "urlList": "https://bit.ly/2WyFVI4",
        "imageUrl": "https://i.imgur.com/PLj6ZYtm.jpg"
    },
    {
        "name": "Jingle",
        "urlList": "https://pastebin.com/raw/7n14SD5g",
        "imageUrl": "https://i.imgur.com/liTBiij.jpg"
    },    
    {
        "name": "L' edicola",
        "urlList": "https://pastebin.com/raw/Jduz7zyC",
        "imageUrl": "https://i.imgur.com/vERwOAF.jpg"
    },
    {
        "name": "Serie Tv",
        "urlList": "https://pastebin.com/raw/U9rxMN9u",
        "imageUrl": "https://i.imgur.com/TPKXO2Wm.jpg"
    },
    {
        "name": "Film",
        "urlList": "https://pastebin.com/raw/PuWtzvE6",
        "imageUrl": "https://i.imgur.com/O8HhNCcm.jpg"
    },
    {
        "name": "Scenette",
        "urlList": "https://pastebin.com/raw/T1JXdtiX",
        "imageUrl": "https://i.imgur.com/bMmqUdR.jpg"
    },
    {
        "name": "Extra musica",
        "urlList": "http://bit.ly/3Eq1T25",
        "imageUrl": "https://i.imgur.com/5jqipBhm.jpg"
    }
]
